{
    "Header": {
        "data_specs_version": "01.00.33",
        "cmor_version": "3.5",
        "table_id": "Table 6hr",
        "realm": "atmos",
        "table_date": "20 June 2023",
        "missing_value": "1e20",
        "int_missing_value": "-999",
        "product": "model-output",
        "approx_interval": "0.25",
        "generic_levels": "",
        "mip_era": "",
        "Conventions": "CF-1.7 ACDD1.3"
    },
    "variable_entry": {
        "orog-6hr": {
            "frequency": "6hr",
            "modeling_realm": "atmos",
            "standard_name": "surface_altitude",
            "units": "m",
            "cell_methods": "area: time: mean",
            "cell_measures": "area: areacella",
            "long_name": "Surface Altitude",
            "comment": "The surface called 'surface' means the lower boundary of the atmosphere. Altitude is the (geometric) height above the geoid, which is the reference geopotential surface. The geoid is similar to mean sea level.",
            "dimensions": "longitude latitude time",
            "out_name": "orog",
            "type": "real",
            "positive": "",
            "valid_min": "",
            "valid_max": "",
            "ok_min_mean_abs": "",
            "ok_max_mean_abs": ""
        },
        "pralsprof-6hr": {
            "frequency": "6hr",
            "modeling_realm": "atmos",
            "standard_name": "stratiform_rainfall_amount",
            "units": "kg m-2",
            "cell_methods": "area: mean time: sum",
            "cell_measures": "area: areacella",
            "long_name": "Stratiform Rainfall Amount",
            "comment": "Stratiform precipitation, whether liquid or frozen, is precipitation that formed in stratiform cloud. 'Amount' means mass per unit area.",
            "dimensions": "longitude latitude time1",
            "out_name": "pralsprof",
            "type": "real",
            "positive": "",
            "valid_min": "",
            "valid_max": "",
            "ok_min_mean_abs": "",
            "ok_max_mean_abs": ""
        },
        "pralsns-6hr": {
            "frequency": "6hr",
            "modeling_realm": "atmos",
            "standard_name": "stratiform_snowfall_amount",
            "units": "kg m-2",
            "cell_methods": "area: mean time: sum",
            "cell_measures": "area: areacella",
            "long_name": "Stratiform Snowfall Amount",
            "comment": "Stratiform precipitation, whether liquid or frozen, is precipitation that formed in stratiform cloud. 'Amount' means mass per unit area.",
            "dimensions": "longitude latitude time1",
            "out_name": "pralsns",
            "type": "real",
            "positive": "",
            "valid_min": "",
            "valid_max": "",
            "ok_min_mean_abs": "",
            "ok_max_mean_abs": ""
        },
        "ua-6hr": {
            "frequency": "6hr",
            "modeling_realm": "atmos",
            "standard_name": "eastward_wind",
            "units": "m s-1",
            "cell_methods": "time: point",
            "cell_measures": "--OPT",
            "long_name": "Eastward Wind",
            "comment": "Zonal wind (positive in a eastward direction).",
            "dimensions": "longitude latitude alevel time1",
            "out_name": "ua",
            "type": "real",
            "positive": "",
            "valid_min": "",
            "valid_max": "",
            "ok_min_mean_abs": "",
            "ok_max_mean_abs": ""
        },
        "va-6hr": {
            "frequency": "6hr",
            "modeling_realm": "atmos",
            "standard_name": "northward_wind",
            "units": "m s-1",
            "cell_methods": "time: point",
            "cell_measures": "--OPT",
            "long_name": "Northward Wind",
            "comment": "Meridional wind (positive in a northward direction).",
            "dimensions": "longitude latitude alevel time1",
            "out_name": "va",
            "type": "real",
            "positive": "",
            "valid_min": "",
            "valid_max": "",
            "ok_min_mean_abs": "",
            "ok_max_mean_abs": ""
        },
        "wa-6hr": {
            "frequency": "6hr",
            "modeling_realm": "atmos",
            "standard_name": "upward_air_velocity",
            "units": "m s-1",
            "cell_methods": "area: time: mean",
            "cell_measures": "area: areacella",
            "long_name": "Upward Air Velocity",
            "comment": "A velocity is a vector quantity. 'Upward' indicates a vector component which is positive when directed upward (negative downward). Upward air velocity is the vertical component of the 3D air velocity vector. The standard name downward_air_velocity may be used for a vector component with the opposite sign convention.",
            "dimensions": "longitude latitude alevel time",
            "out_name": "wa",
            "type": "real",
            "positive": "",
            "valid_min": "",
            "valid_max": "",
            "ok_min_mean_abs": "",
            "ok_max_mean_abs": ""
        },
        "wbptemp-6hr": {
            "frequency": "6hr",
            "modeling_realm": "atmos",
            "standard_name": "wet_bulb_potential_temperature",
            "units": "K",
            "cell_methods": "area: mean time: point",
            "cell_measures": "area: areacella",
            "long_name": "Wet Bulb Potential Temperature",
            "comment": "Wet bulb potential temperature",
            "dimensions": "longitude latitude plev7h time1",
            "out_name": "wbptemp",
            "type": "real",
            "positive": "",
            "valid_min": "",
            "valid_max": "",
            "ok_min_mean_abs": "",
            "ok_max_mean_abs": ""
        },
        "zg-6hr": {
            "frequency": "6hr",
            "modeling_realm": "atmos",
            "standard_name": "geopotential_height",
            "units": "m",
            "cell_methods": "area: mean time: point",
            "cell_measures": "area: areacella",
            "long_name": "Geopotential Height",
            "comment": "Geopotential is the sum of the specific gravitational potential energy relative to the geoid and the specific centripetal potential energy. Geopotential height is the geopotential divided by the standard acceleration due to gravity. It is numerically similar to the altitude (or geometric height) and not to the quantity with standard name height, which is relative to the surface.",
            "dimensions": "longitude latitude plev27 time1",
            "out_name": "zg",
            "type": "real",
            "positive": "",
            "valid_min": "",
            "valid_max": "",
            "ok_min_mean_abs": "",
            "ok_max_mean_abs": ""
        },
        "ta-6hr": {
            "frequency": "6hr",
            "modeling_realm": "atmos",
            "standard_name": "air_temperature",
            "units": "K",
            "cell_methods": "area: mean time: point",
            "cell_measures": "area: areacella",
            "long_name": "Air Temperature",
            "comment": "Air Temperature",
            "dimensions": "longitude latitude alevel time1",
            "out_name": "ta",
            "type": "real",
            "positive": "",
            "valid_min": "",
            "valid_max": "",
            "ok_min_mean_abs": "",
            "ok_max_mean_abs": ""
        },
        "hur-6hr": {
            "frequency": "6hr",
            "modeling_realm": "atmos",
            "standard_name": "relative_humidity",
            "units": "%",
            "cell_methods": "time: mean",
            "cell_measures": "area: areacella",
            "long_name": "Relative Humidity",
            "comment": "The relative humidity with respect to liquid water for T> 0 C, and with respect to ice for T<0 C.",
            "dimensions": "longitude latitude plev19 time",
            "out_name": "hur",
            "type": "real",
            "positive": "",
            "valid_min": "",
            "valid_max": "",
            "ok_min_mean_abs": "",
            "ok_max_mean_abs": ""
        }
    }
}